fmri_anonymizer/__init__.py
fmri_anonymizer/__main__.py
fmri_anonymizer/deidentifier.py
fmri_anonymizer/directory_replicator.py
fmri_anonymizer/file_searcher.py
tests/__init__.py
fmri_anonymizer-0.0.2.dist-info/LICENSE
fmri_anonymizer-0.0.2.dist-info/METADATA
fmri_anonymizer-0.0.2.dist-info/WHEEL
fmri_anonymizer-0.0.2.dist-info/entry_points.txt
fmri_anonymizer-0.0.2.dist-info/top_level.txt
fmri_anonymizer-0.0.2.dist-info/RECORD
