Metadata-Version: 2.1
Name: fmri-anonymizer
Version: 0.0.2
Summary: Anonymize your DICOM and NIFTI files with this tool easily.
Home-page: https://caoslab.psy.cmu.edu:32443/hugoanda/fmri_anonymizer
Author: Hugo Angulo
Author-email: hugoanda@andrew.cmu.edu
License: MIT
Platform: UNKNOWN
Classifier: License :: OSI Approved :: MIT License
Classifier: Programming Language :: Python :: 3
Classifier: Programming Language :: Python :: 3.7
Requires-Python: >=3.7
Requires-Dist: deid
Requires-Dist: dicom2nifti
Requires-Dist: pydeface
Requires-Dist: numpy
Requires-Dist: nibabel
Requires-Dist: nipype
Requires-Dist: ttictoc
